[
    {
        "name": "BlindDeck",
        "tid": "Blind Deck Challenge",
        "card_level_adjustment": "Friendly",
        "deck_selection": "Predefined",
        "overtime_seconds": 180,
        "predefined_decks": [
            "CRLWorlds_Queso",
            "CRLWorlds_Nova",
            "CRLWorlds_Ponos",
            "CRLWorlds_Vivo",
            "CRLWorlds_Immortals",
            "CRLWorlds_KZDX"
        ],
        "separate_team_decks": true,
        "players": "PvP",
        "icon": "icon_mode_popdeck",
        "clan_war_description": "Play with a premade Classic Deck!",
        "battle_start_cooldown": 6000,
        "id": 72000000,
        "name_en": "Blind Deck Challenge"
    },
    {
        "name": "DoubleElixir",
        "tid": "Double Elixir Battle",
        "card_level_adjustment": "Tournament",
        "deck_selection": "Collection",
        "overtime_seconds": 180,
        "elixir_production_multiplier": 200,
        "use_starting_elixir": true,
        "starting_elixir": 0,
        "players": "PvP",
        "icon": "icon_mode_2x_elixir",
        "clan_war_description": "Elixir generates at double speed!",
        "skin_set": "ElixerPump",
        "id": 72000001,
        "name_en": "Double Elixir Battle"
    },
    {
        "name": "ThreeBridges",
        "tid": "Three Bridges Challenge",
        "card_level_adjustment": "Tournament",
        "deck_selection": "Collection",
        "overtime_seconds": 180,
        "players": "PvP",
        "id": 72000002,
        "name_en": "Three Bridges Challenge"
    },
    {
        "name": "HeroChallenge_draft",
        "tid": "Heroes Challenge",
        "card_level_adjustment": "Tournament",
        "deck_selection": "Draft",
        "overtime_seconds": 180,
        "heroes": true,
        "players": "PvP",
        "dark_elixir_spawn_interval": 14000,
        "id": 72000003,
        "name_en": "Heroes Challenge"
    },
    {
        "name": "ElectroWiz",
        "tid": "Electro Wizard Challenge",
        "card_level_adjustment": "Friendly",
        "deck_selection": "EventDeck",
        "overtime_seconds": 180,
        "forced_deck_cards": "ElectroWizard",
        "players": "PvP",
        "id": 72000004,
        "name_en": "Electro Wizard Challenge"
    },
    {
        "name": "DraftMode",
        "tid": "Draft Battle",
        "request_tid": "Join Draft Battle!",
        "in_progress_tid": "Draft Battle: <cfffffe><time></c>",
        "card_level_adjustment": "Friendly",
        "deck_selection": "Draft",
        "overtime_seconds": 180,
        "players": "PvP",
        "icon": "icon_mode_draft",
        "clan_war_description": "Choose 4 cards and receive 4 from your opponent!",
        "id": 72000005,
        "name_en": "Draft Battle"
    },
    {
        "name": "Ladder",
        "card_level_adjustment": "Ladder",
        "deck_selection": "Collection",
        "overtime_seconds": 60,
        "players": "PvP",
        "id": 72000006,
        "name_en": "Ladder"
    },
    {
        "name": "Friendly",
        "tid": "1v1 Battle",
        "card_level_adjustment": "Friendly",
        "deck_selection": "Collection",
        "overtime_seconds": 180,
        "players": "PvP",
        "icon": "icon_mode_1v1",
        "id": 72000007,
        "name_en": "1v1 Battle"
    },
    {
        "name": "Training",
        "card_level_adjustment": "Ladder",
        "deck_selection": "Collection",
        "overtime_seconds": 60,
        "players": "PvP",
        "id": 72000008,
        "name_en": "Training"
    },
    {
        "name": "Tournament",
        "tid": "Normal Battle",
        "card_level_adjustment": "Tournament",
        "deck_selection": "Collection",
        "overtime_seconds": 180,
        "players": "PvP",
        "icon": "icon_tournament_bronze",
        "id": 72000009,
        "name_en": "Normal Battle"
    },
    {
        "name": "Challenge",
        "tid": "Normal Battle",
        "card_level_adjustment": "Tournament",
        "deck_selection": "Collection",
        "overtime_seconds": 180,
        "players": "PvP",
        "icon": "icon_tournament_bronze",
        "id": 72000010,
        "name_en": "Normal Battle"
    },
    {
        "name": "DoubleElixir_Friendly",
        "tid": "Double Elixir Battle",
        "request_tid": "Join Double Elixir Battle!",
        "in_progress_tid": "Double Elixir Battle: <cfffffe><time></c>",
        "card_level_adjustment": "Friendly",
        "deck_selection": "Collection",
        "overtime_seconds": 180,
        "elixir_production_multiplier": 200,
        "use_starting_elixir": true,
        "starting_elixir": 0,
        "players": "PvP",
        "icon": "icon_mode_2x_elixir",
        "clan_war_description": "Elixir generates at double speed!",
        "skin_set": "ElixerPump",
        "id": 72000011,
        "name_en": "Double Elixir Battle"
    },
    {
        "name": "BattleRam",
        "tid": "Electro Wizard Challenge",
        "card_level_adjustment": "Friendly",
        "deck_selection": "EventDeck",
        "overtime_seconds": 180,
        "players": "PvP",
        "id": 72000012,
        "name_en": "Electro Wizard Challenge"
    },
    {
        "name": "DraftModeInsane",
        "tid": "Double Elixir Draft",
        "request_tid": "Join Double Elixir Draft Battle!",
        "in_progress_tid": "Double Elixir Draft: <cfffffe><time></c>",
        "card_level_adjustment": "Friendly",
        "deck_selection": "Draft",
        "overtime_seconds": 180,
        "elixir_production_multiplier": 200,
        "use_starting_elixir": true,
        "starting_elixir": 0,
        "players": "PvP",
        "icon": "icon_mode_2x_elixir_draft",
        "id": 72000013,
        "name_en": "Double Elixir Draft"
    },
    {
        "name": "TeamVsTeam",
        "tid": "2v2 Battle",
        "card_level_adjustment": "Friendly",
        "deck_selection": "Collection",
        "overtime_seconds": 180,
        "elixir_production_multiplier": 85,
        "elixir_production_overtime_multiplier": 70,
        "players": "TvT",
        "icon": "icon_mode_2v2",
        "id": 72000014,
        "name_en": "2v2 Battle"
    },
    {
        "name": "RetroRoyale",
        "tid": "Retro Royale Challenge",
        "card_level_adjustment": "Friendly",
        "deck_selection": "EventDeck",
        "overtime_seconds": 180,
        "players": "PvP",
        "event_deck_set_limit": "Event_Retro",
        "icon": "icon_mode_retro",
        "id": 72000015,
        "name_en": "Retro Royale Challenge"
    },
    {
        "name": "CardRelease",
        "card_level_adjustment": "Friendly",
        "deck_selection": "EventDeck",
        "overtime_seconds": 180,
        "players": "PvP",
        "forced_deck_cards_using_card_theme": true,
        "id": 72000016,
        "name_en": "CardRelease"
    },
    {
        "name": "CardReleaseDraft",
        "tid": "Draft Battle",
        "request_tid": "Join Draft Battle!",
        "in_progress_tid": "Draft Battle: <cfffffe><time></c>",
        "card_level_adjustment": "Friendly",
        "deck_selection": "Draft",
        "overtime_seconds": 180,
        "players": "PvP",
        "forced_deck_cards_using_card_theme": true,
        "id": 72000017,
        "name_en": "Draft Battle"
    },
    {
        "name": "PvE",
        "tid": "Puzzle Royale",
        "card_level_adjustment": "Friendly",
        "deck_selection": "Collection",
        "overtime_seconds": 60,
        "elixir_production_multiplier": 300,
        "use_starting_elixir": true,
        "starting_elixir": 10,
        "players": "PvE",
        "id": 72000018,
        "name_en": "Puzzle Royale"
    },
    {
        "name": "TvE",
        "tid": "Clan vs Enemy",
        "card_level_adjustment": "Friendly",
        "deck_selection": "Collection",
        "overtime_seconds": 60,
        "elixir_production_multiplier": 85,
        "elixir_production_overtime_multiplier": 70,
        "use_starting_elixir": true,
        "starting_elixir": 0,
        "players": "TvE",
        "id": 72000019,
        "name_en": "Clan vs Enemy"
    },
    {
        "name": "PvE_Boss",
        "tid": "Puzzle Royale",
        "card_level_adjustment": "Friendly",
        "deck_selection": "Collection",
        "overtime_seconds": 60,
        "use_starting_elixir": true,
        "starting_elixir": 10,
        "players": "PvE",
        "id": 72000020,
        "name_en": "Puzzle Royale"
    },
    {
        "name": "PvE_Tutorial",
        "tid": "Puzzle Royale",
        "card_level_adjustment": "Ladder",
        "deck_selection": "Collection",
        "overtime_seconds": 60,
        "players": "PvE",
        "id": 72000021,
        "name_en": "Puzzle Royale"
    },
    {
        "name": "TeamVsTeamDraft",
        "tid": "2v2 Draft Battle",
        "request_tid": "Join 2v2 Draft Battle!",
        "in_progress_tid": "2v2 Draft Battle: <cfffffe><time></c>",
        "card_level_adjustment": "Friendly",
        "deck_selection": "Draft",
        "overtime_seconds": 180,
        "elixir_production_multiplier": 85,
        "elixir_production_overtime_multiplier": 70,
        "players": "TvT",
        "icon": "icon_mode_draft",
        "id": 72000022,
        "name_en": "2v2 Draft Battle"
    },
    {
        "name": "TeamVsTeamLadder",
        "tid": "2v2 Battle",
        "card_level_adjustment": "Ladder",
        "deck_selection": "Collection",
        "overtime_seconds": 180,
        "elixir_production_multiplier": 85,
        "elixir_production_overtime_multiplier": 70,
        "players": "TvT",
        "icon": "icon_mode_2v2",
        "clan_war_description": "Play with a Clanmate!",
        "id": 72000023,
        "name_en": "2v2 Battle"
    },
    {
        "name": "Overtime_Tournament",
        "tid": "Sudden Death Battle",
        "card_level_adjustment": "Tournament",
        "deck_selection": "Collection",
        "overtime_seconds": 180,
        "use_starting_elixir": true,
        "starting_elixir": 0,
        "players": "PvP",
        "icon": "icon_mode_suddendeath",
        "clan_war_description": "The first player to take a tower... WINS!",
        "id": 72000024,
        "name_en": "Sudden Death Battle"
    },
    {
        "name": "GoldRush_Tournament",
        "tid": "Gold Rush",
        "card_level_adjustment": "Tournament",
        "deck_selection": "Collection",
        "overtime_seconds": 180,
        "players": "PvP",
        "gold_per_tower1": 100,
        "gold_per_tower2": 200,
        "gold_per_tower3": 500,
        "end_confetti1": "win_battle_confetti_gold",
        "end_confetti2": "win_battle_confetti_gold_top",
        "skin_set": "GoldRush",
        "id": 72000025,
        "name_en": "Gold Rush"
    },
    {
        "name": "TeamVsTeamChallenge",
        "tid": "2v2 Challenge",
        "card_level_adjustment": "Tournament",
        "deck_selection": "Collection",
        "overtime_seconds": 180,
        "elixir_production_multiplier": 85,
        "elixir_production_overtime_multiplier": 70,
        "players": "TvT",
        "id": 72000026,
        "name_en": "2v2 Challenge"
    },
    {
        "name": "TripleElixir_Tournament",
        "tid": "Triple Elixir Battle",
        "card_level_adjustment": "Tournament",
        "deck_selection": "Collection",
        "overtime_seconds": 180,
        "elixir_production_multiplier": 300,
        "elixir_production_overtime_multiplier": 150,
        "use_starting_elixir": true,
        "starting_elixir": 0,
        "players": "PvP",
        "icon": "icon_mode_3x_elixir",
        "clan_war_description": "Elixir generates at triple speed!",
        "skin_set": "ElixerPump",
        "id": 72000027,
        "name_en": "Triple Elixir Battle"
    },
    {
        "name": "RampUpElixir_Tournament",
        "tid": "Ramp Up Battle",
        "card_level_adjustment": "Tournament",
        "deck_selection": "Collection",
        "overtime_seconds": 180,
        "players": "PvP",
        "icon": "icon_mode_ramp_up",
        "clan_war_description": "Elixir generates faster and faster throughout the battle!",
        "id": 72000028,
        "name_en": "Ramp Up Battle"
    },
    {
        "name": "TeamVsTeamCrowns",
        "tid": "2v2 Battle",
        "card_level_adjustment": "Friendly",
        "deck_selection": "Collection",
        "overtime_seconds": 180,
        "elixir_production_multiplier": 85,
        "elixir_production_overtime_multiplier": 70,
        "players": "TvT",
        "gives_clan_score": true,
        "id": 72000029,
        "name_en": "2v2 Battle"
    },
    {
        "name": "TeamVsTeamDraftChallenge",
        "tid": "2v2 Draft Battle",
        "request_tid": "Join 2v2 Draft Battle!",
        "in_progress_tid": "2v2 Draft Battle: <cfffffe><time></c>",
        "card_level_adjustment": "Friendly",
        "deck_selection": "Draft",
        "overtime_seconds": 180,
        "elixir_production_multiplier": 85,
        "elixir_production_overtime_multiplier": 70,
        "players": "TvT",
        "icon": "icon_mode_draft",
        "clan_war_description": "Choose 4 cards and receive 4 from your opponent!",
        "id": 72000030,
        "name_en": "2v2 Draft Battle"
    },
    {
        "name": "Overtime_Friendly",
        "tid": "Sudden Death Battle",
        "request_tid": "Join Sudden Death Battle!",
        "in_progress_tid": "Sudden Death Battle: <cfffffe><time></c>",
        "card_level_adjustment": "Friendly",
        "deck_selection": "Collection",
        "overtime_seconds": 180,
        "use_starting_elixir": true,
        "starting_elixir": 0,
        "players": "PvP",
        "icon": "icon_mode_suddendeath",
        "clan_war_description": "The first player to take a tower... WINS!",
        "id": 72000031,
        "name_en": "Sudden Death Battle"
    },
    {
        "name": "TripleElixir_Friendly",
        "tid": "Triple Elixir Battle",
        "request_tid": "Join Triple Elixir Battle!",
        "in_progress_tid": "Triple Elixir Battle: <cfffffe><time></c>",
        "card_level_adjustment": "Friendly",
        "deck_selection": "Collection",
        "overtime_seconds": 180,
        "elixir_production_multiplier": 300,
        "elixir_production_overtime_multiplier": 150,
        "use_starting_elixir": true,
        "starting_elixir": 0,
        "players": "PvP",
        "icon": "icon_mode_3x_elixir",
        "clan_war_description": "Elixir generates at triple speed!",
        "skin_set": "ElixerPump",
        "id": 72000032,
        "name_en": "Triple Elixir Battle"
    },
    {
        "name": "RampUpElixir_Friendly",
        "tid": "Ramp Up Battle",
        "request_tid": "Join Ramp Up Battle!",
        "in_progress_tid": "Ramp Up Battle: <cfffffe><time></c>",
        "card_level_adjustment": "Friendly",
        "deck_selection": "Collection",
        "overtime_seconds": 180,
        "players": "PvP",
        "icon": "icon_mode_ramp_up",
        "clan_war_description": "Elixir generates faster and faster throughout the battle!",
        "id": 72000033,
        "name_en": "Ramp Up Battle"
    },
    {
        "name": "TeamVsTeam_DoubleElixir_Friendly",
        "tid": "2v2 Double Elixir",
        "request_tid": "Join 2v2 Double Elixir Battle!",
        "in_progress_tid": "2v2 Double Elixir Battle: <cfffffe><time></c>",
        "card_level_adjustment": "Friendly",
        "deck_selection": "Collection",
        "overtime_seconds": 180,
        "elixir_production_multiplier": 170,
        "elixir_production_overtime_multiplier": 85,
        "use_starting_elixir": true,
        "starting_elixir": 0,
        "players": "TvT",
        "clan_war_description": "Elixir generates at double speed!",
        "id": 72000034,
        "name_en": "2v2 Double Elixir"
    },
    {
        "name": "TeamVsTeam_DoubleElixir_Tournament",
        "tid": "2v2 Double Elixir",
        "card_level_adjustment": "Tournament",
        "deck_selection": "Collection",
        "overtime_seconds": 180,
        "elixir_production_multiplier": 170,
        "elixir_production_overtime_multiplier": 85,
        "use_starting_elixir": true,
        "starting_elixir": 0,
        "players": "TvT",
        "clan_war_description": "Elixir generates at double speed!",
        "id": 72000035,
        "name_en": "2v2 Double Elixir"
    },
    {
        "name": "TeamVsTeam_Overtime_Friendly",
        "tid": "2v2 Sudden Death",
        "request_tid": "Join 2v2 Sudden Death Battle!",
        "in_progress_tid": "2v2 Sudden Death Battle: <cfffffe><time></c>",
        "card_level_adjustment": "Friendly",
        "deck_selection": "Collection",
        "overtime_seconds": 180,
        "elixir_production_multiplier": 85,
        "elixir_production_overtime_multiplier": 70,
        "players": "TvT",
        "icon": "icon_mode_suddendeath",
        "clan_war_description": "The first player to take a tower... WINS!",
        "id": 72000036,
        "name_en": "2v2 Sudden Death"
    },
    {
        "name": "TeamVsTeam_Overtime_Tournament",
        "tid": "2v2 Sudden Death",
        "card_level_adjustment": "Tournament",
        "deck_selection": "Collection",
        "overtime_seconds": 180,
        "elixir_production_multiplier": 85,
        "elixir_production_overtime_multiplier": 70,
        "players": "TvT",
        "icon": "icon_mode_suddendeath",
        "clan_war_description": "The first player to take a tower... WINS!",
        "id": 72000037,
        "name_en": "2v2 Sudden Death"
    },
    {
        "name": "TeamVsTeam_RampUpElixir_Friendly",
        "tid": "2v2 Ramp Up",
        "request_tid": "Join 2v2 Ramp Up Battle!",
        "in_progress_tid": "2v2 Ramp Up Battle: <cfffffe><time></c>",
        "card_level_adjustment": "Friendly",
        "deck_selection": "Collection",
        "overtime_seconds": 180,
        "elixir_production_multiplier": 85,
        "elixir_production_overtime_multiplier": 85,
        "players": "TvT",
        "clan_war_description": "Elixir generates faster and faster throughout the battle!",
        "id": 72000038,
        "name_en": "2v2 Ramp Up"
    },
    {
        "name": "TeamVsTeam_RampUpElixir_Tournament",
        "tid": "2v2 Ramp Up",
        "card_level_adjustment": "Tournament",
        "deck_selection": "Collection",
        "overtime_seconds": 180,
        "elixir_production_multiplier": 85,
        "elixir_production_overtime_multiplier": 85,
        "players": "TvT",
        "clan_war_description": "Elixir generates faster and faster throughout the battle!",
        "id": 72000039,
        "name_en": "2v2 Ramp Up"
    },
    {
        "name": "TeamVsTeam_DraftModeInsane_Friendly",
        "tid": "2v2 Double Elixir Draft",
        "request_tid": "Join 2v2 Double Elixir Draft Battle!",
        "in_progress_tid": "2v2 Double Elixir Draft: <cfffffe><time></c>",
        "card_level_adjustment": "Friendly",
        "deck_selection": "Draft",
        "overtime_seconds": 180,
        "elixir_production_multiplier": 170,
        "elixir_production_overtime_multiplier": 140,
        "use_starting_elixir": true,
        "starting_elixir": 0,
        "players": "TvT",
        "icon": "icon_mode_2x_elixir_draft",
        "id": 72000040,
        "name_en": "2v2 Double Elixir Draft"
    },
    {
        "name": "Invalid",
        "card_level_adjustment": "Friendly",
        "deck_selection": "Collection",
        "overtime_seconds": 180,
        "players": "PvP",
        "id": 72000041,
        "name_en": "Invalid"
    },
    {
        "name": "PickMode",
        "tid": "Draft Pick Challenge",
        "card_level_adjustment": "Friendly",
        "deck_selection": "Pick",
        "overtime_seconds": 180,
        "players": "PvP",
        "id": 72000042,
        "name_en": "Draft Pick Challenge"
    },
    {
        "name": "TeamVsTeamLadder_GoldRush",
        "tid": "Gold Rush",
        "card_level_adjustment": "Ladder",
        "deck_selection": "Collection",
        "overtime_seconds": 180,
        "elixir_production_multiplier": 85,
        "elixir_production_overtime_multiplier": 70,
        "players": "TvT",
        "gold_per_tower1": 100,
        "gold_per_tower2": 200,
        "gold_per_tower3": 500,
        "end_confetti1": "win_battle_confetti_gold",
        "end_confetti2": "win_battle_confetti_gold_top",
        "skin_set": "GoldRush",
        "id": 72000043,
        "name_en": "Gold Rush"
    },
    {
        "name": "Ladder_GoldRush",
        "tid": "Gold Rush",
        "card_level_adjustment": "Ladder",
        "deck_selection": "Collection",
        "overtime_seconds": 60,
        "players": "PvP",
        "gold_per_tower1": 100,
        "gold_per_tower2": 200,
        "gold_per_tower3": 500,
        "end_confetti1": "win_battle_confetti_gold",
        "end_confetti2": "win_battle_confetti_gold_top",
        "skin_set": "GoldRush",
        "id": 72000044,
        "name_en": "Gold Rush"
    },
    {
        "name": "Touchdown",
        "tid": "Touchdown",
        "request_tid": "Join the Friendly Touchdown!",
        "in_progress_tid": "Touchdown Battle: <cfffffe><time></c>",
        "card_level_adjustment": "Ladder",
        "deck_selection": "Collection",
        "overtime_seconds": 180,
        "players": "PvP",
        "target_touchdowns": 3,
        "icon": "icon_mode_touchdown",
        "fixed_arena": "Arena_TouchdownTest",
        "clan_war_description": "Get a troop into your opponent's end zone to score!",
        "skin_set": "Touchdown",
        "id": 72000045,
        "name_en": "Touchdown"
    },
    {
        "name": "TeamVsTeamLadder_GemRush",
        "tid": "Gem Rush",
        "card_level_adjustment": "Ladder",
        "deck_selection": "Collection",
        "overtime_seconds": 180,
        "elixir_production_multiplier": 85,
        "elixir_production_overtime_multiplier": 70,
        "players": "TvT",
        "gems_per_tower1": 3,
        "gems_per_tower2": 5,
        "gems_per_tower3": 10,
        "end_confetti1": "win_battle_confetti_gem",
        "end_confetti2": "win_battle_confetti_gem_top",
        "id": 72000046,
        "name_en": "Gem Rush"
    },
    {
        "name": "Ladder_GemRush",
        "tid": "Gem Rush",
        "card_level_adjustment": "Ladder",
        "deck_selection": "Collection",
        "overtime_seconds": 60,
        "players": "PvP",
        "gems_per_tower1": 3,
        "gems_per_tower2": 5,
        "gems_per_tower3": 10,
        "end_confetti1": "win_battle_confetti_gem",
        "end_confetti2": "win_battle_confetti_gem_top",
        "id": 72000047,
        "name_en": "Gem Rush"
    },
    {
        "name": "GemRush_Tournament",
        "tid": "Gem Rush",
        "card_level_adjustment": "Tournament",
        "deck_selection": "Collection",
        "overtime_seconds": 180,
        "players": "PvP",
        "gems_per_tower1": 3,
        "gems_per_tower2": 5,
        "gems_per_tower3": 10,
        "end_confetti1": "win_battle_confetti_gem",
        "end_confetti2": "win_battle_confetti_gem_top",
        "id": 72000048,
        "name_en": "Gem Rush"
    },
    {
        "name": "TeamVsTeam_Touchdown",
        "tid": "2v2 Touchdown",
        "request_tid": "Join the Friendly 2v2 Touchdown!",
        "in_progress_tid": "2v2 Touchdown Battle: <cfffffe><time></c>",
        "card_level_adjustment": "Friendly",
        "deck_selection": "Collection",
        "overtime_seconds": 180,
        "elixir_production_multiplier": 85,
        "elixir_production_overtime_multiplier": 70,
        "players": "TvT",
        "target_touchdowns": 3,
        "fixed_arena": "Arena_TouchdownTest",
        "clan_war_description": "Get a troop into your opponent's end zone to score!",
        "skin_set": "Touchdown",
        "id": 72000049,
        "name_en": "2v2 Touchdown"
    },
    {
        "name": "Touchdown_Draft",
        "tid": "Touchdown Draft",
        "request_tid": "Join the Friendly Touchdown!",
        "in_progress_tid": "Touchdown Battle: <cfffffe><time></c>",
        "card_level_adjustment": "Friendly",
        "deck_selection": "Draft",
        "overtime_seconds": 180,
        "players": "PvP",
        "target_touchdowns": 3,
        "icon": "icon_mode_touchdown",
        "clan_war_description": "Get a troop into your opponent's end zone to score!",
        "skin_set": "Touchdown",
        "id": 72000050,
        "name_en": "Touchdown Draft"
    },
    {
        "name": "TeamVsTeam_Touchdown_Draft",
        "tid": "2v2 Touchdown Draft",
        "request_tid": "Join the Friendly 2v2 Touchdown!",
        "in_progress_tid": "2v2 Touchdown Battle: <cfffffe><time></c>",
        "card_level_adjustment": "Friendly",
        "deck_selection": "Draft",
        "overtime_seconds": 180,
        "elixir_production_multiplier": 85,
        "elixir_production_overtime_multiplier": 70,
        "players": "TvT",
        "target_touchdowns": 3,
        "icon": "icon_mode_touchdown",
        "fixed_arena": "Arena_TouchdownTest",
        "clan_war_description": "Get a troop into your opponent's end zone to score!",
        "skin_set": "Touchdown",
        "id": 72000051,
        "name_en": "2v2 Touchdown Draft"
    },
    {
        "name": "MirrorDeck",
        "tid": "Mirror Battle",
        "request_tid": "Join the Friendly Mirror Battle!",
        "in_progress_tid": "Mirror Battle: <cfffffe><time></c>",
        "card_level_adjustment": "Friendly",
        "deck_selection": "Predefined",
        "overtime_seconds": 180,
        "predefined_decks": [
            "MirrorDeck"
        ],
        "same_deck_on_both": true,
        "players": "PvP",
        "icon": "icon_mode_mirror",
        "clan_war_description": "You have the exact same deck and starting cards as your opponent!",
        "battle_start_cooldown": 6000,
        "id": 72000052,
        "name_en": "Mirror Battle"
    },
    {
        "name": "TeamVsTeam_MirrorDeck",
        "tid": "2v2 Mirror Battle",
        "request_tid": "Join the Friendly 2v2 Mirror Battle!",
        "in_progress_tid": "2v2 Mirror Battle: <cfffffe><time></c>",
        "card_level_adjustment": "Friendly",
        "deck_selection": "Predefined",
        "overtime_seconds": 180,
        "predefined_decks": [
            "MirrorDeck2v2"
        ],
        "same_deck_on_both": true,
        "separate_team_decks": true,
        "players": "TvT",
        "icon": "icon_mode_mirror",
        "clan_war_description": "You have the exact same deck and starting cards as your opponent!",
        "id": 72000053,
        "name_en": "2v2 Mirror Battle"
    },
    {
        "name": "Friendly_FixedDeckOrder",
        "tid": "1v1 Fixed Deck Battle",
        "request_tid": "Join 1v1 Fixed Deck Battle!",
        "in_progress_tid": "1v1 Fixed Deck Battle: <cfffffe><time></c>",
        "card_level_adjustment": "Friendly",
        "deck_selection": "Collection",
        "overtime_seconds": 180,
        "players": "PvP",
        "fixed_deck_order": true,
        "icon": "icon_mode_1v1",
        "id": 72000054,
        "name_en": "1v1 Fixed Deck Battle"
    },
    {
        "name": "TeamVsTeam_FixedDeckOrder",
        "tid": "2v2 Fixed Deck Battle",
        "request_tid": "Join 2v2 Fixed Deck Battle!",
        "in_progress_tid": "2v2 Fixed Deck Battle: <cfffffe><time></c>",
        "card_level_adjustment": "Friendly",
        "deck_selection": "Collection",
        "overtime_seconds": 180,
        "elixir_production_multiplier": 85,
        "elixir_production_overtime_multiplier": 70,
        "players": "TvT",
        "fixed_deck_order": true,
        "icon": "icon_mode_2v2",
        "id": 72000055,
        "name_en": "2v2 Fixed Deck Battle"
    },
    {
        "name": "MirrorDeck_H",
        "tid": "Mirror Battle",
        "request_tid": "Join the Friendly Mirror Battle!",
        "in_progress_tid": "Mirror Battle: <cfffffe><time></c>",
        "card_level_adjustment": "Friendly",
        "deck_selection": "Predefined",
        "overtime_seconds": 180,
        "predefined_decks": [
            "MirrorDeck_H"
        ],
        "same_deck_on_both": true,
        "players": "PvP",
        "icon": "icon_mode_mirror",
        "clan_war_description": "You have the exact same deck and starting cards as your opponent!",
        "id": 72000056,
        "name_en": "Mirror Battle"
    },
    {
        "name": "TeamVsTeam_MirrorDeck_H",
        "tid": "2v2 Mirror Battle",
        "request_tid": "Join the Friendly 2v2 Mirror Battle!",
        "in_progress_tid": "2v2 Mirror Battle: <cfffffe><time></c>",
        "card_level_adjustment": "Friendly",
        "deck_selection": "Predefined",
        "overtime_seconds": 180,
        "predefined_decks": [
            "MirrorDeck2v2_H"
        ],
        "same_deck_on_both": true,
        "separate_team_decks": true,
        "players": "TvT",
        "icon": "icon_mode_mirror",
        "clan_war_description": "You have the exact same deck and starting cards as your opponent!",
        "id": 72000057,
        "name_en": "2v2 Mirror Battle"
    },
    {
        "name": "KingOfTheHill",
        "tid": "King of the Hill",
        "request_tid": "Join the Friendly King of the Hill!",
        "in_progress_tid": "King of the Hill Battle: <cfffffe><time></c>",
        "card_level_adjustment": "Friendly",
        "deck_selection": "Collection",
        "overtime_seconds": 60,
        "elixir_production_multiplier": 85,
        "elixir_production_overtime_multiplier": 70,
        "players": "PvP",
        "id": 72000058,
        "name_en": "King of the Hill"
    },
    {
        "name": "ModernRoyale",
        "tid": "Modern Royale",
        "card_level_adjustment": "Friendly",
        "deck_selection": "EventDeck",
        "overtime_seconds": 180,
        "players": "PvP",
        "event_deck_set_limit": "Event_Modern",
        "icon": "icon_mode_retro",
        "id": 72000059,
        "name_en": "Modern Royale"
    },
    {
        "name": "Overtime_Ladder",
        "tid": "Sudden Death Battle",
        "request_tid": "Join Sudden Death Battle!",
        "in_progress_tid": "Sudden Death Battle: <cfffffe><time></c>",
        "card_level_adjustment": "Ladder",
        "deck_selection": "Collection",
        "overtime_seconds": 180,
        "use_starting_elixir": true,
        "starting_elixir": 0,
        "players": "PvP",
        "icon": "icon_mode_suddendeath",
        "clan_war_description": "The first player to take a tower... WINS!",
        "id": 72000060,
        "name_en": "Sudden Death Battle"
    },
    {
        "name": "DoubleElixir_Ladder",
        "tid": "Double Elixir Battle",
        "request_tid": "Join Double Elixir Battle!",
        "in_progress_tid": "Double Elixir Battle: <cfffffe><time></c>",
        "card_level_adjustment": "Ladder",
        "deck_selection": "Collection",
        "overtime_seconds": 180,
        "elixir_production_multiplier": 200,
        "use_starting_elixir": true,
        "starting_elixir": 0,
        "players": "PvP",
        "icon": "icon_mode_2x_elixir",
        "clan_war_description": "Elixir generates at double speed!",
        "skin_set": "ElixerPump",
        "id": 72000061,
        "name_en": "Double Elixir Battle"
    },
    {
        "name": "TripleElixir_Ladder",
        "tid": "Triple Elixir Battle",
        "request_tid": "Join Triple Elixir Battle!",
        "in_progress_tid": "Triple Elixir Battle: <cfffffe><time></c>",
        "card_level_adjustment": "Ladder",
        "deck_selection": "Collection",
        "overtime_seconds": 180,
        "elixir_production_multiplier": 300,
        "elixir_production_overtime_multiplier": 150,
        "use_starting_elixir": true,
        "starting_elixir": 0,
        "players": "PvP",
        "icon": "icon_mode_3x_elixir",
        "clan_war_description": "Elixir generates at triple speed!",
        "skin_set": "ElixerPump",
        "id": 72000062,
        "name_en": "Triple Elixir Battle"
    },
    {
        "name": "NOTINUSE1",
        "tid": "2v2 Double Elixir",
        "request_tid": "Join 2v2 Double Elixir Battle!",
        "in_progress_tid": "2v2 Double Elixir Battle: <cfffffe><time></c>",
        "card_level_adjustment": "Ladder",
        "deck_selection": "Collection",
        "overtime_seconds": 180,
        "elixir_production_multiplier": 170,
        "elixir_production_overtime_multiplier": 85,
        "use_starting_elixir": true,
        "starting_elixir": 0,
        "players": "TvT",
        "icon": "icon_mode_2x_elixir",
        "id": 72000063,
        "name_en": "2v2 Double Elixir"
    },
    {
        "name": "NOTINUSE2",
        "tid": "2v2 Double Elixir",
        "request_tid": "Join 2v2 Double Elixir Battle!",
        "in_progress_tid": "2v2 Double Elixir Battle: <cfffffe><time></c>",
        "card_level_adjustment": "Ladder",
        "deck_selection": "Collection",
        "overtime_seconds": 180,
        "elixir_production_multiplier": 170,
        "elixir_production_overtime_multiplier": 85,
        "use_starting_elixir": true,
        "starting_elixir": 0,
        "players": "TvT",
        "icon": "icon_mode_2x_elixir",
        "id": 72000064,
        "name_en": "2v2 Double Elixir"
    },
    {
        "name": "Showdown_Friendly",
        "tid": "War Deck Battle",
        "card_level_adjustment": "Friendly",
        "deck_selection": "Collection",
        "overtime_seconds": 180,
        "players": "PvP",
        "icon": "icon_clan_wars",
        "clan_war_description": "Build a War Deck using the Clan Cards and enter the Arena. You get one Final Battle to score a win for your Clan - no pressure!",
        "id": 72000065,
        "name_en": "War Deck Battle"
    },
    {
        "name": "Showdown_Ladder",
        "tid": "War Deck Battle",
        "card_level_adjustment": "Ladder",
        "deck_selection": "Collection",
        "overtime_seconds": 180,
        "players": "PvP",
        "icon": "icon_clan_wars",
        "clan_war_description": "Build a War Deck using the Clan Cards and enter the Arena. You get one Final Battle to score a win for your Clan - no pressure!",
        "id": 72000066,
        "name_en": "War Deck Battle"
    },
    {
        "name": "TeamVsTeam_DoubleElixir_Ladder",
        "tid": "2v2 Double Elixir",
        "request_tid": "Join 2v2 Double Elixir Battle!",
        "in_progress_tid": "2v2 Double Elixir Battle: <cfffffe><time></c>",
        "card_level_adjustment": "Ladder",
        "deck_selection": "Collection",
        "overtime_seconds": 180,
        "elixir_production_multiplier": 170,
        "elixir_production_overtime_multiplier": 85,
        "use_starting_elixir": true,
        "starting_elixir": 0,
        "players": "TvT",
        "icon": "icon_mode_2x_elixir",
        "clan_war_description": "Elixir generates at double speed!",
        "id": 72000067,
        "name_en": "2v2 Double Elixir"
    },
    {
        "name": "TeamVsTeam_Overtime_Ladder",
        "tid": "2v2 Sudden Death",
        "request_tid": "Join 2v2 Sudden Death Battle!",
        "in_progress_tid": "2v2 Sudden Death Battle: <cfffffe><time></c>",
        "card_level_adjustment": "Ladder",
        "deck_selection": "Collection",
        "overtime_seconds": 180,
        "use_starting_elixir": true,
        "starting_elixir": 0,
        "players": "TvT",
        "icon": "icon_mode_suddendeath",
        "clan_war_description": "The first player to take a tower... WINS!",
        "id": 72000068,
        "name_en": "2v2 Sudden Death"
    },
    {
        "name": "CaptureTower_Friendly",
        "tid": "Capture Tower",
        "request_tid": "Join Capture Tower Battle!",
        "in_progress_tid": "Capture Tower Battle: <cfffffe><time></c>",
        "card_level_adjustment": "Friendly",
        "deck_selection": "Collection",
        "overtime_seconds": 180,
        "players": "PvP",
        "icon": "icon_mode_suddendeath",
        "id": 72000069,
        "name_en": "Capture Tower"
    },
    {
        "name": "RampUpElixir_Ladder",
        "tid": "Ramp Up Battle",
        "request_tid": "Join Ramp Up Battle!",
        "in_progress_tid": "Ramp Up Battle: <cfffffe><time></c>",
        "card_level_adjustment": "Ladder",
        "deck_selection": "Collection",
        "overtime_seconds": 180,
        "players": "PvP",
        "icon": "icon_mode_ramp_up",
        "clan_war_description": "Elixir generates faster and faster throughout the battle!",
        "id": 72000070,
        "name_en": "Ramp Up Battle"
    },
    {
        "name": "Rage_Friendly",
        "tid": "Rage Battle",
        "request_tid": "Join Rage Battle!",
        "in_progress_tid": "Rage Battle: <cfffffe><time></c>",
        "card_level_adjustment": "Friendly",
        "deck_selection": "Collection",
        "overtime_seconds": 180,
        "elixir_production_multiplier": 135,
        "players": "PvP",
        "icon": "icon_mode_rage",
        "fixed_arena": "Arena5",
        "global_buff": "RageModeRage",
        "looping_effect": "Rage_mode",
        "id": 72000071,
        "name_en": "Rage Battle"
    },
    {
        "name": "MirrorDeck_CW",
        "tid": "Mirror Battle",
        "request_tid": "Join the Friendly Mirror Battle!",
        "in_progress_tid": "Mirror Battle: <cfffffe><time></c>",
        "card_level_adjustment": "Friendly",
        "deck_selection": "Predefined",
        "overtime_seconds": 180,
        "predefined_decks": [
            "MirrorDeck_CW"
        ],
        "same_deck_on_both": true,
        "players": "PvP",
        "icon": "icon_mode_mirror",
        "clan_war_description": "You have the exact same deck and starting cards as your opponent!",
        "battle_start_cooldown": 6000,
        "id": 72000072,
        "name_en": "Mirror Battle"
    },
    {
        "name": "Rage_Ladder",
        "tid": "Rage Battle",
        "request_tid": "Join Rage Battle!",
        "in_progress_tid": "Rage Battle: <cfffffe><time></c>",
        "card_level_adjustment": "Ladder",
        "deck_selection": "Collection",
        "overtime_seconds": 180,
        "elixir_production_multiplier": 135,
        "players": "PvP",
        "icon": "icon_mode_rage",
        "fixed_arena": "Arena5",
        "clan_war_description": "Someone spilt Rage all over the Arena... Everything moves and attacks faster!",
        "global_buff": "RageModeRage",
        "looping_effect": "Rage_mode",
        "id": 72000073,
        "name_en": "Rage Battle"
    },
    {
        "name": "LavaFloor_Friendly",
        "tid": "Lava Floor Battle",
        "request_tid": "Join Lava Floor Battle!",
        "in_progress_tid": "Lava Floor Battle: <cfffffe><time></c>",
        "card_level_adjustment": "Friendly",
        "deck_selection": "Collection",
        "overtime_seconds": 180,
        "elixir_production_multiplier": 135,
        "players": "PvP",
        "icon": "icon_mode_rage",
        "fixed_arena": "Arena4",
        "global_buff": "PoisonModePoison",
        "looping_effect": "LavaFloor_mode",
        "id": 72000074,
        "name_en": "Lava Floor Battle"
    },
    {
        "name": "Event_NewArena1",
        "tid": "Arena 1 Deckbuilding Challenge",
        "card_level_adjustment": "Friendly",
        "deck_selection": "EventDeck",
        "overtime_seconds": 180,
        "players": "PvP",
        "event_deck_set_limit": "Event_NewUnlockA1",
        "icon": "icon_mode_retro",
        "fixed_arena": "Arena1",
        "id": 72000075,
        "name_en": "Arena 1 Deckbuilding Challenge"
    },
    {
        "name": "Event_NewArena2",
        "tid": "Arena 2 Deckbuilding Challenge",
        "card_level_adjustment": "Friendly",
        "deck_selection": "EventDeck",
        "overtime_seconds": 180,
        "players": "PvP",
        "event_deck_set_limit": "Event_NewUnlockA2",
        "icon": "icon_mode_retro",
        "fixed_arena": "Arena2",
        "id": 72000076,
        "name_en": "Arena 2 Deckbuilding Challenge"
    },
    {
        "name": "Event_NewArena3",
        "tid": "Arena 3 Deckbuilding Challenge",
        "card_level_adjustment": "Friendly",
        "deck_selection": "EventDeck",
        "overtime_seconds": 180,
        "players": "PvP",
        "event_deck_set_limit": "Event_NewUnlockA3",
        "icon": "icon_mode_retro",
        "fixed_arena": "Arena3",
        "id": 72000077,
        "name_en": "Arena 3 Deckbuilding Challenge"
    },
    {
        "name": "Event_NewArena4",
        "tid": "Arena 4 Deckbuilding Challenge",
        "card_level_adjustment": "Friendly",
        "deck_selection": "EventDeck",
        "overtime_seconds": 180,
        "players": "PvP",
        "event_deck_set_limit": "Event_NewUnlockA4",
        "icon": "icon_mode_retro",
        "fixed_arena": "Arena4",
        "id": 72000078,
        "name_en": "Arena 4 Deckbuilding Challenge"
    },
    {
        "name": "Event_NewArena5",
        "tid": "Arena 5 Deckbuilding Challenge",
        "card_level_adjustment": "Friendly",
        "deck_selection": "EventDeck",
        "overtime_seconds": 180,
        "players": "PvP",
        "event_deck_set_limit": "Event_NewUnlockA5",
        "icon": "icon_mode_retro",
        "fixed_arena": "Arena5",
        "id": 72000079,
        "name_en": "Arena 5 Deckbuilding Challenge"
    },
    {
        "name": "Event_NewArena6",
        "tid": "Arena 6 Deckbuilding Challenge",
        "card_level_adjustment": "Friendly",
        "deck_selection": "EventDeck",
        "overtime_seconds": 180,
        "players": "PvP",
        "event_deck_set_limit": "Event_NewUnlockA6",
        "icon": "icon_mode_retro",
        "fixed_arena": "Arena6",
        "id": 72000080,
        "name_en": "Arena 6 Deckbuilding Challenge"
    },
    {
        "name": "Event_NewArena7",
        "tid": "Arena 7 Deckbuilding Challenge",
        "card_level_adjustment": "Friendly",
        "deck_selection": "EventDeck",
        "overtime_seconds": 180,
        "players": "PvP",
        "event_deck_set_limit": "Event_NewUnlockA7",
        "icon": "icon_mode_retro",
        "fixed_arena": "Arena7",
        "id": 72000081,
        "name_en": "Arena 7 Deckbuilding Challenge"
    },
    {
        "name": "Event_NewArena8",
        "tid": "Arena 8 Deckbuilding Challenge",
        "card_level_adjustment": "Friendly",
        "deck_selection": "EventDeck",
        "overtime_seconds": 180,
        "players": "PvP",
        "event_deck_set_limit": "Event_NewUnlockA8",
        "icon": "icon_mode_retro",
        "fixed_arena": "Arena8",
        "id": 72000082,
        "name_en": "Arena 8 Deckbuilding Challenge"
    },
    {
        "name": "Event_NewArena9",
        "tid": "Arena 9 Deckbuilding Challenge",
        "card_level_adjustment": "Friendly",
        "deck_selection": "EventDeck",
        "overtime_seconds": 180,
        "players": "PvP",
        "event_deck_set_limit": "Event_NewUnlockA9",
        "icon": "icon_mode_retro",
        "fixed_arena": "Arena9",
        "id": 72000083,
        "name_en": "Arena 9 Deckbuilding Challenge"
    },
    {
        "name": "Event_NewArena10",
        "tid": "Arena 10 Deckbuilding Challenge",
        "card_level_adjustment": "Friendly",
        "deck_selection": "EventDeck",
        "overtime_seconds": 180,
        "players": "PvP",
        "event_deck_set_limit": "Event_NewUnlockA10",
        "icon": "icon_mode_retro",
        "fixed_arena": "Arena_L",
        "id": 72000084,
        "name_en": "Arena 10 Deckbuilding Challenge"
    },
    {
        "name": "Event_NewArena11",
        "tid": "Arena 11 Deckbuilding Challenge",
        "card_level_adjustment": "Friendly",
        "deck_selection": "EventDeck",
        "overtime_seconds": 180,
        "players": "PvP",
        "event_deck_set_limit": "Event_NewUnlockA11",
        "icon": "icon_mode_retro",
        "fixed_arena": "Arena_Electric",
        "id": 72000085,
        "name_en": "Arena 11 Deckbuilding Challenge"
    },
    {
        "name": "Rage_Tournament",
        "tid": "Rage Battle",
        "request_tid": "Join Rage Battle!",
        "in_progress_tid": "Rage Battle: <cfffffe><time></c>",
        "card_level_adjustment": "Tournament",
        "deck_selection": "Collection",
        "overtime_seconds": 180,
        "elixir_production_multiplier": 135,
        "players": "PvP",
        "icon": "icon_mode_rage",
        "fixed_arena": "Arena5",
        "global_buff": "RageModeRage",
        "looping_effect": "Rage_mode",
        "id": 72000086,
        "name_en": "Rage Battle"
    },
    {
        "name": "ClassicDecks_Friendly",
        "tid": "Classic Decks Battle",
        "request_tid": "Join Classic Decks Battle!",
        "in_progress_tid": "Classic Decks Battle in progress: <cfffffe><time></c>",
        "card_level_adjustment": "Friendly",
        "deck_selection": "Predefined",
        "overtime_seconds": 180,
        "predefined_decks": [
            "Blind_Classic_HogQuake",
            "Blind_Classic_RamRush",
            "Blind_Classic_GiantPrince",
            "Blind_Classic_Balloon",
            "Blind_Classic_Golem",
            "Blind_Classic_Graveyard"
        ],
        "separate_team_decks": true,
        "players": "PvP",
        "icon": "icon_mode_popdeck",
        "clan_war_description": "Play with a premade Classic Deck!",
        "battle_start_cooldown": 6000,
        "id": 72000087,
        "name_en": "Classic Decks Battle"
    },
    {
        "name": "TeamVsTeam_Rage_Ladder",
        "tid": "2v2 Rage Mode",
        "request_tid": "Join 2v2 Rage Battle!",
        "in_progress_tid": "2v2 Rage Battle: <cfffffe><time></c>",
        "card_level_adjustment": "Ladder",
        "deck_selection": "Collection",
        "overtime_seconds": 180,
        "elixir_production_multiplier": 115,
        "elixir_production_overtime_multiplier": 85,
        "players": "TvT",
        "icon": "icon_mode_rage",
        "fixed_arena": "Arena5",
        "clan_war_description": "Someone spilt Rage all over the Arena... Everything moves and attacks faster!",
        "global_buff": "RageModeRage",
        "looping_effect": "Rage_mode",
        "id": 72000088,
        "name_en": "2v2 Rage Mode"
    },
    {
        "name": "ThreeVsThree",
        "tid": "3v3",
        "request_tid": "Requesting 3v3!",
        "in_progress_tid": "3v3 in progress",
        "card_level_adjustment": "Friendly",
        "deck_selection": "Collection",
        "overtime_seconds": 180,
        "elixir_production_multiplier": 85,
        "elixir_production_overtime_multiplier": 70,
        "players": "3v3",
        "icon": "icon_mode_2v2",
        "heist": true,
        "id": 72000089,
        "name_en": "3v3"
    },
    {
        "name": "ThreeVsThreeHeist",
        "tid": "3v3 Heist",
        "request_tid": "Requesting 3v3 heist!",
        "in_progress_tid": "3v3 heist in progress",
        "card_level_adjustment": "Friendly",
        "deck_selection": "Collection",
        "overtime_seconds": 180,
        "elixir_production_multiplier": 85,
        "elixir_production_overtime_multiplier": 70,
        "players": "3v3",
        "icon": "icon_mode_2v2",
        "heist": true,
        "id": 72000090,
        "name_en": "3v3 Heist"
    },
    {
        "name": "Heist_Friendly",
        "tid": "Heist",
        "request_tid": "Requesting Heist Battle!",
        "in_progress_tid": "Heist battle in progress",
        "card_level_adjustment": "Friendly",
        "deck_selection": "Collection",
        "overtime_seconds": 180,
        "elixir_production_multiplier": 150,
        "elixir_production_overtime_multiplier": 80,
        "players": "PvP",
        "icon": "icon_tournament_heist",
        "heist": true,
        "id": 72000091,
        "name_en": "Heist"
    },
    {
        "name": "Heist_Draft",
        "tid": "Heist Draft",
        "request_tid": "Requesting Heist Draft Battle!",
        "in_progress_tid": "Heist Draft battle in progress",
        "card_level_adjustment": "Friendly",
        "deck_selection": "Draft",
        "overtime_seconds": 180,
        "elixir_production_multiplier": 150,
        "elixir_production_overtime_multiplier": 80,
        "players": "PvP",
        "icon": "icon_tournament_heist",
        "heist": true,
        "id": 72000092,
        "name_en": "Heist Draft"
    },
    {
        "name": "Event_Shocktober",
        "tid": "Shocktober Challenge",
        "card_level_adjustment": "Friendly",
        "deck_selection": "EventDeck",
        "overtime_seconds": 180,
        "players": "PvP",
        "event_deck_set_limit": "Event_Shocktober",
        "icon": "icon_mode_1v1",
        "fixed_arena": "Arena_Electric",
        "id": 72000093,
        "name_en": "Shocktober Challenge"
    },
    {
        "name": "HeroChallenge1v1",
        "tid": "Heroes Challenge",
        "card_level_adjustment": "Tournament",
        "deck_selection": "Collection",
        "overtime_seconds": 180,
        "heroes": true,
        "players": "PvP",
        "auto_generate_dark_elixir": 21000,
        "has_dark_elixir_collector": true,
        "id": 72000094,
        "name_en": "Heroes Challenge"
    },
    {
        "name": "TeamVsTeam_TripleElixir_Ladder",
        "tid": "Triple Elixir Battle",
        "request_tid": "Join Triple Elixir Battle!",
        "in_progress_tid": "Triple Elixir Battle: <cfffffe><time></c>",
        "card_level_adjustment": "Ladder",
        "deck_selection": "Collection",
        "overtime_seconds": 180,
        "elixir_production_multiplier": 255,
        "elixir_production_overtime_multiplier": 150,
        "use_starting_elixir": true,
        "starting_elixir": 0,
        "players": "TvT",
        "icon": "icon_mode_3x_elixir",
        "clan_war_description": "Elixir generates at triple speed!",
        "skin_set": "ElixerPump",
        "id": 72000095,
        "name_en": "Triple Elixir Battle"
    },
    {
        "name": "Heist_Tournament",
        "tid": "Heist",
        "request_tid": "Requesting Heist Battle!",
        "in_progress_tid": "Heist battle in progress",
        "card_level_adjustment": "Tournament",
        "deck_selection": "Collection",
        "overtime_seconds": 180,
        "elixir_production_multiplier": 150,
        "elixir_production_overtime_multiplier": 80,
        "players": "PvP",
        "icon": "icon_tournament_heist",
        "heist": true,
        "id": 72000096,
        "name_en": "Heist"
    },
    {
        "name": "SpawnPigsMode_Friendly",
        "tid": "Hog Race",
        "card_level_adjustment": "Friendly",
        "deck_selection": "Collection",
        "overtime_seconds": 180,
        "players": "PvP",
        "icon": "icon_mode_1v1",
        "spawn_character": "RoyalHog",
        "spawn_character_interval": 12000,
        "spawn_character_count": 2,
        "spawn_character_start_delay": 10000,
        "id": 72000097,
        "name_en": "Hog Race"
    },
    {
        "name": "ClanWarMiniCollection_Friendly",
        "tid": "Clan War Deck Mode",
        "card_level_adjustment": "Friendly",
        "deck_selection": "EventDeck",
        "overtime_seconds": 180,
        "players": "PvP",
        "event_deck_clan_war": true,
        "icon": "icon_mode_retro",
        "deck_spell_sets": [
            "MiniCollect_WinCon",
            "MiniCollect_WinCon",
            "MiniCollect_SmallSpell",
            "MiniCollect_SmallSpell",
            "MiniCollect_BigSpell",
            "MiniCollect_BigSpell",
            "MiniCollect_AntiTank",
            "MiniCollect_AntiAir",
            "MiniCollect_AntiAir",
            "MiniCollect_DefensiveBuilding"
        ],
        "anti_spell_sets": [
            "MiniCollect_AntiSet_Expensive",
            "MiniCollect_AntiSet_Buildings"
        ],
        "id": 72000098,
        "name_en": "Clan War Deck Mode"
    },
    {
        "name": "ClassicDecks_Helsinki2016",
        "tid": "Classic Decks: Helsinki 2016",
        "request_tid": "Join Classic Decks Battle!",
        "in_progress_tid": "Classic Decks Battle in progress: <cfffffe><time></c>",
        "card_level_adjustment": "Friendly",
        "deck_selection": "Predefined",
        "overtime_seconds": 180,
        "predefined_decks": [
            "ClassicHKI_Jason",
            "ClassicHKI_Elfe",
            "ClassicHKI_Naazime",
            "ClassicHKI_Steroidi",
            "ClassicHKI_ClashWithAsh"
        ],
        "players": "PvP",
        "icon": "icon_mode_popdeck",
        "clan_war_description": "Play with a Classic Deck from the 1st Esports tournament - Helsinki 2016!",
        "id": 72000099,
        "name_en": "Classic Decks: Helsinki 2016"
    },
    {
        "name": "ClassicDecks_KingsCup1",
        "tid": "Classic Decks: King's Cup 1",
        "request_tid": "Join Classic Decks Battle!",
        "in_progress_tid": "Classic Decks Battle in progress: <cfffffe><time></c>",
        "card_level_adjustment": "Friendly",
        "deck_selection": "Predefined",
        "overtime_seconds": 180,
        "predefined_decks": [
            "ClassicKC1_YaoYao",
            "ClassicKC1_Colton",
            "ClassicKC1_ChiefPat",
            "ClassicKC1_TopNotch"
        ],
        "players": "PvP",
        "icon": "icon_mode_popdeck",
        "clan_war_description": "Play with a Classic Deck from King's Cup 1!",
        "id": 72000100,
        "name_en": "Classic Decks: King's Cup 1"
    },
    {
        "name": "ClanWarMiniCollection_Ladder",
        "tid": "Clan War Deck Mode",
        "card_level_adjustment": "Ladder",
        "deck_selection": "EventDeck",
        "overtime_seconds": 180,
        "players": "PvP",
        "event_deck_clan_war": true,
        "icon": "icon_mode_retro",
        "deck_spell_sets": [
            "MiniCollect_WinCon",
            "MiniCollect_WinCon",
            "MiniCollect_SmallSpell",
            "MiniCollect_SmallSpell",
            "MiniCollect_BigSpell",
            "MiniCollect_BigSpell",
            "MiniCollect_AntiTank",
            "MiniCollect_AntiAir",
            "MiniCollect_AntiAir",
            "MiniCollect_DefensiveBuilding"
        ],
        "anti_spell_sets": [
            "MiniCollect_AntiSet_Expensive",
            "MiniCollect_AntiSet_Buildings"
        ],
        "id": 72000101,
        "name_en": "Clan War Deck Mode"
    },
    {
        "name": "ClanWarMiniCollection_Tournament",
        "tid": "Clan War Deck Mode",
        "card_level_adjustment": "Tournament",
        "deck_selection": "EventDeck",
        "overtime_seconds": 180,
        "players": "PvP",
        "event_deck_clan_war": true,
        "icon": "icon_mode_retro",
        "deck_spell_sets": [
            "MiniCollect_WinCon",
            "MiniCollect_WinCon",
            "MiniCollect_SmallSpell",
            "MiniCollect_SmallSpell",
            "MiniCollect_BigSpell",
            "MiniCollect_BigSpell",
            "MiniCollect_AntiTank",
            "MiniCollect_AntiAir",
            "MiniCollect_AntiAir",
            "MiniCollect_DefensiveBuilding"
        ],
        "anti_spell_sets": [
            "MiniCollect_AntiSet_Expensive",
            "MiniCollect_AntiSet_Buildings"
        ],
        "id": 72000102,
        "name_en": "Clan War Deck Mode"
    },
    {
        "name": "Boosts_Friendly",
        "tid": "Random Boosts",
        "card_level_adjustment": "Friendly",
        "deck_selection": "Collection",
        "overtime_seconds": 180,
        "random_boosts": true,
        "players": "PvP",
        "icon": "icon_mode_1v1",
        "id": 72000103,
        "name_en": "Random Boosts"
    },
    {
        "name": "Snowball_bombardment",
        "tid": "Snowball bombardment",
        "card_level_adjustment": "Friendly",
        "deck_selection": "Collection",
        "overtime_seconds": 180,
        "players": "PvP",
        "icon": "icon_mode_1v1",
        "spawn_character_interval": 6000,
        "spawn_character_start_delay": 8000,
        "spawn_projectile": "SnowballSpell",
        "id": 72000104,
        "name_en": "Snowball bombardment"
    },
    {
        "name": "RampUpElixirSpawnPigsMode_Friendly",
        "tid": "Hog Race",
        "card_level_adjustment": "Friendly",
        "deck_selection": "Collection",
        "overtime_seconds": 180,
        "players": "PvP",
        "icon": "icon_mode_1v1",
        "spawn_character": "RoyalHog",
        "spawn_character_interval": 12000,
        "spawn_character_count": 1,
        "spawn_character_start_delay": 13500,
        "id": 72000105,
        "name_en": "Hog Race"
    },
    {
        "name": "DraftSpawnPigsMode_Friendly",
        "tid": "Hog Race",
        "card_level_adjustment": "Friendly",
        "deck_selection": "Draft",
        "overtime_seconds": 180,
        "players": "PvP",
        "icon": "icon_mode_1v1",
        "spawn_character": "RoyalHog",
        "spawn_character_interval": 12000,
        "spawn_character_count": 1,
        "spawn_character_start_delay": 13500,
        "id": 72000106,
        "name_en": "Hog Race"
    },
    {
        "name": "RampUpElixirSpawnPigsMode_Tournament",
        "tid": "Hog Race",
        "card_level_adjustment": "Tournament",
        "deck_selection": "Collection",
        "overtime_seconds": 180,
        "players": "PvP",
        "icon": "icon_mode_1v1",
        "spawn_character": "RoyalHog",
        "spawn_character_interval": 12000,
        "spawn_character_count": 1,
        "spawn_character_start_delay": 13500,
        "id": 72000107,
        "name_en": "Hog Race"
    },
    {
        "name": "EventDeckrSpawnPigsMode_Tournament",
        "tid": "Hog Race",
        "card_level_adjustment": "Tournament",
        "deck_selection": "EventDeck",
        "overtime_seconds": 180,
        "players": "PvP",
        "icon": "icon_mode_1v1",
        "spawn_character": "RoyalHog",
        "spawn_character_interval": 12000,
        "spawn_character_count": 1,
        "spawn_character_start_delay": 13500,
        "id": 72000108,
        "name_en": "Hog Race"
    },
    {
        "name": "RampUpElixirEventDeckSpawnPigsMode_Friendly",
        "tid": "Hog Race",
        "card_level_adjustment": "Friendly",
        "deck_selection": "EventDeck",
        "overtime_seconds": 180,
        "players": "PvP",
        "icon": "icon_mode_1v1",
        "spawn_character": "RoyalHog",
        "spawn_character_interval": 12000,
        "spawn_character_count": 1,
        "spawn_character_start_delay": 13500,
        "id": 72000109,
        "name_en": "Hog Race"
    },
    {
        "name": "RampUpElixirDraftSpawnPigsMode_Friendly",
        "tid": "Hog Race",
        "card_level_adjustment": "Friendly",
        "deck_selection": "Draft",
        "overtime_seconds": 180,
        "players": "PvP",
        "icon": "icon_mode_1v1",
        "spawn_character": "RoyalHog",
        "spawn_character_interval": 12000,
        "spawn_character_count": 1,
        "spawn_character_start_delay": 13500,
        "id": 72000110,
        "name_en": "Hog Race"
    },
    {
        "name": "TeamVsTeamSpellSupportDraft",
        "tid": "2v2 Draft Battle",
        "request_tid": "Join 2v2 Draft Battle!",
        "in_progress_tid": "2v2 Draft Battle: <cfffffe><time></c>",
        "card_level_adjustment": "Friendly",
        "deck_selection": "Draft",
        "overtime_seconds": 180,
        "elixir_production_multiplier": 85,
        "elixir_production_overtime_multiplier": 70,
        "players": "TvT",
        "icon": "icon_mode_draft",
        "spell_support": true,
        "id": 72000111,
        "name_en": "2v2 Draft Battle"
    },
    {
        "name": "RampFatigue",
        "tid": "Ramp Up Fatigue Mode",
        "card_level_adjustment": "Friendly",
        "deck_selection": "Collection",
        "overtime_seconds": 120,
        "players": "PvP",
        "icon": "icon_mode_1v1",
        "fatigue_amount": 100,
        "fatigue_interval": 2000,
        "id": 72000112,
        "name_en": "Ramp Up Fatigue Mode"
    },
    {
        "name": "TestBuff",
        "tid": "Snowball bombardment",
        "card_level_adjustment": "Friendly",
        "deck_selection": "Collection",
        "overtime_seconds": 180,
        "players": "PvP",
        "icon": "icon_mode_1v1",
        "buff_character": "MiniPekka",
        "buff_name": "Invisibility",
        "id": 72000113,
        "name_en": "Snowball bombardment"
    },
    {
        "name": "HeroChallenge_draft2",
        "tid": "Heroes Challenge",
        "card_level_adjustment": "Tournament",
        "deck_selection": "Draft",
        "overtime_seconds": 180,
        "heroes": true,
        "players": "PvP",
        "auto_generate_dark_elixir": 14000,
        "id": 72000114,
        "name_en": "Heroes Challenge"
    },
    {
        "name": "HeroChallenge_draft3",
        "tid": "Heroes Challenge",
        "card_level_adjustment": "Tournament",
        "deck_selection": "Draft",
        "overtime_seconds": 180,
        "heroes": true,
        "players": "PvP",
        "auto_generate_dark_elixir": 21000,
        "has_dark_elixir_collector": true,
        "capturable_building": "DarkElixirCollector",
        "id": 72000115,
        "name_en": "Heroes Challenge"
    },
    {
        "name": "ElixirCollectorCapture_Friendly",
        "tid": "1v1 Battle",
        "card_level_adjustment": "Friendly",
        "deck_selection": "Collection",
        "overtime_seconds": 180,
        "players": "PvP",
        "icon": "icon_mode_1v1",
        "capturable_building": "ElixirCollectorNeutral",
        "capturable_building_respawn_interval": 31500,
        "elixir_spawn_interval": 21000,
        "id": 72000116,
        "name_en": "1v1 Battle"
    },
    {
        "name": "CaptureTheEgg_Friendly",
        "tid": "1v1 Battle",
        "card_level_adjustment": "Friendly",
        "deck_selection": "Collection",
        "overtime_seconds": 180,
        "players": "PvP",
        "icon": "icon_mode_1v1",
        "capturable_building": "DragonEgg",
        "capturable_building_respawn_interval": 31500,
        "id": 72000117,
        "name_en": "1v1 Battle"
    },
    {
        "name": "DoubleDeck_Friendly",
        "tid": "Mega Deck",
        "card_level_adjustment": "Friendly",
        "deck_selection": "Collection",
        "overtime_seconds": 180,
        "elixir_production_multiplier": 125,
        "elixir_production_overtime_multiplier": 125,
        "players": "PvP",
        "icon": "icon_mode_1v1",
        "deck_size": 16,
        "id": 72000118,
        "name_en": "Mega Deck"
    },
    {
        "name": "DoubleDeck_Tournament",
        "tid": "Mega Deck",
        "card_level_adjustment": "Tournament",
        "deck_selection": "EventDeck",
        "overtime_seconds": 180,
        "elixir_production_multiplier": 125,
        "elixir_production_overtime_multiplier": 125,
        "players": "PvP",
        "icon": "icon_mode_1v1",
        "deck_size": 18,
        "id": 72000119,
        "name_en": "Mega Deck"
    },
    {
        "name": "RampUpElixirRageJacksMode_Tournament",
        "tid": "Lumberjack Rush",
        "card_level_adjustment": "Tournament",
        "deck_selection": "Collection",
        "overtime_seconds": 180,
        "elixir_production_multiplier": 135,
        "players": "PvP",
        "icon": "icon_mode_rage",
        "fixed_arena": "Arena8",
        "global_buff": "RageModeRage",
        "looping_effect": "Rage_mode",
        "spawn_character": "RageBarbarian",
        "spawn_character_interval": 18000,
        "spawn_character_count": 1,
        "spawn_character_start_delay": 13500,
        "id": 72000120,
        "name_en": "Lumberjack Rush"
    },
    {
        "name": "EventDeck_Rage_SpawnJacks_Friendly",
        "tid": "Lumberjack Rage Rush",
        "card_level_adjustment": "Friendly",
        "deck_selection": "EventDeck",
        "overtime_seconds": 180,
        "elixir_production_multiplier": 135,
        "players": "PvP",
        "forced_deck_cards_using_card_theme": true,
        "icon": "icon_mode_1v1",
        "spawn_character": "RageBarbarian",
        "spawn_character_interval": 19000,
        "spawn_character_count": 1,
        "spawn_character_start_delay": 19000,
        "id": 72000121,
        "name_en": "Lumberjack Rage Rush"
    },
    {
        "name": "Draft_Rage_SpawnJacks_Friendly",
        "tid": "Lumberjack Rage Draft",
        "card_level_adjustment": "Friendly",
        "deck_selection": "Draft",
        "overtime_seconds": 180,
        "elixir_production_multiplier": 135,
        "players": "PvP",
        "icon": "icon_mode_draft",
        "spawn_character": "RageBarbarian",
        "spawn_character_interval": 19000,
        "spawn_character_count": 1,
        "spawn_character_start_delay": 19000,
        "id": 72000122,
        "name_en": "Lumberjack Rage Draft"
    },
    {
        "name": "ElixirCollectorCapture_Tournament",
        "tid": "Elixir Capture",
        "card_level_adjustment": "Tournament",
        "deck_selection": "Collection",
        "overtime_seconds": 180,
        "players": "PvP",
        "icon": "icon_mode_1v1",
        "capturable_building": "ElixirCollectorNeutral",
        "capturable_building_respawn_interval": 31500,
        "elixir_spawn_interval": 21000,
        "id": 72000123,
        "name_en": "Elixir Capture"
    },
    {
        "name": "CaptureTheEgg_Tournament",
        "tid": "Dragon Hunt",
        "card_level_adjustment": "Tournament",
        "deck_selection": "Collection",
        "overtime_seconds": 180,
        "players": "PvP",
        "icon": "icon_mode_1v1",
        "capturable_building": "DragonEgg",
        "capturable_building_respawn_interval": 31500,
        "id": 72000124,
        "name_en": "Dragon Hunt"
    },
    {
        "name": "Obstacles_Friendly",
        "tid": "1v1 Battle",
        "card_level_adjustment": "Friendly",
        "deck_selection": "Collection",
        "overtime_seconds": 180,
        "players": "PvP",
        "icon": "icon_mode_1v1",
        "fixed_arena": "Arena_Obstacles",
        "id": 72000125,
        "name_en": "1v1 Battle"
    },
    {
        "name": "Mega_Boss_PVE",
        "tid": "1v1 Battle",
        "card_level_adjustment": "Friendly",
        "deck_selection": "Collection",
        "overtime_seconds": 180,
        "players": "PvE",
        "icon": "icon_mode_1v1",
        "id": 72000126,
        "name_en": "1v1 Battle"
    },
    {
        "name": "CaptureTheFish_Friendly",
        "tid": "1v1 Battle",
        "card_level_adjustment": "Friendly",
        "deck_selection": "Collection",
        "overtime_seconds": 180,
        "players": "PvP",
        "icon": "icon_mode_1v1",
        "capturable_building": "FishBoat",
        "capturable_building_respawn_interval": 31500,
        "id": 72000127,
        "name_en": "1v1 Battle"
    },
    {
        "name": "RockyBoat_Friendly",
        "tid": "1v1 Battle",
        "card_level_adjustment": "Friendly",
        "deck_selection": "Collection",
        "overtime_seconds": 180,
        "players": "PvP",
        "icon": "icon_mode_1v1",
        "elixir_spawn_interval": 21000,
        "id": 72000128,
        "name_en": "1v1 Battle"
    },
    {
        "name": "BlindDeck_FloodHounds",
        "tid": "Take To The Skies",
        "request_tid": "Join Classic Decks Battle!",
        "in_progress_tid": "Classic Decks Battle in progress: <cfffffe><time></c>",
        "card_level_adjustment": "Friendly",
        "deck_selection": "Predefined",
        "overtime_seconds": 180,
        "predefined_decks": [
            "FloodHounds_1",
            "FloodHounds_2",
            "FloodHounds_3",
            "FloodHounds_4"
        ],
        "separate_team_decks": true,
        "elixir_production_multiplier": 200,
        "players": "PvP",
        "icon": "icon_mode_popdeck",
        "fixed_arena": "Arena_Flood",
        "clan_war_description": "Play with a Classic Deck from King's Cup 1!",
        "id": 72000129,
        "name_en": "Take To The Skies"
    },
    {
        "name": "Neutral_Fisherman",
        "tid": "1v1 Battle",
        "card_level_adjustment": "Friendly",
        "deck_selection": "Collection",
        "overtime_seconds": 180,
        "players": "PvP",
        "icon": "icon_mode_1v1",
        "neutral_character": "Fisherbarrel",
        "id": 72000130,
        "name_en": "1v1 Battle"
    },
    {
        "name": "ClassicDecks2_Friendly",
        "tid": "Classic Decks Battle",
        "request_tid": "Join Classic Decks Battle!",
        "in_progress_tid": "Classic Decks Battle in progress: <cfffffe><time></c>",
        "card_level_adjustment": "Friendly",
        "deck_selection": "Predefined",
        "overtime_seconds": 180,
        "predefined_decks": [
            "Blind_Classic_RoyalHogs",
            "Blind_Classic_MegaKnight",
            "Blind_Classic_Mortar",
            "Blind_Classic_GoblinGiant",
            "Blind_Classic_Xbow",
            "Blind_Classic_LavaLoon"
        ],
        "separate_team_decks": true,
        "players": "PvP",
        "icon": "icon_mode_popdeck",
        "clan_war_description": "Play with a premade Classic Deck!",
        "battle_start_cooldown": 6000,
        "id": 72000131,
        "name_en": "Classic Decks Battle"
    },
    {
        "name": "Heist_Ladder",
        "tid": "Heist",
        "request_tid": "Requesting Heist Battle!",
        "in_progress_tid": "Heist battle in progress",
        "card_level_adjustment": "Ladder",
        "deck_selection": "Collection",
        "overtime_seconds": 180,
        "elixir_production_multiplier": 150,
        "elixir_production_overtime_multiplier": 150,
        "players": "PvP",
        "icon": "icon_tournament_heist",
        "clan_war_description": "Towers are replaced with a lone defenceless safe. Destroy the safe to win!",
        "heist": true,
        "id": 72000132,
        "name_en": "Heist"
    },
    {
        "name": "RampUpElixirSpawnWBsMode_Tournament",
        "tid": "Wall Breaker Party",
        "card_level_adjustment": "Tournament",
        "deck_selection": "Collection",
        "overtime_seconds": 180,
        "players": "PvP",
        "icon": "icon_mode_1v1",
        "clan_war_description": "Wall Breakers run from the Towers periodically, defend your Tower walls!",
        "spawn_character": "Wallbreaker",
        "spawn_character_interval": 15000,
        "spawn_character_count": 2,
        "spawn_character_start_delay": 5000,
        "id": 72000133,
        "name_en": "Wall Breaker Party"
    },
    {
        "name": "RampUpElixirSpawnWBsMode_Ladder",
        "tid": "Wall Breaker Party",
        "card_level_adjustment": "Ladder",
        "deck_selection": "Collection",
        "overtime_seconds": 180,
        "players": "PvP",
        "icon": "icon_mode_1v1",
        "clan_war_description": "Wall Breakers run from the Towers periodically, defend your Tower walls!",
        "spawn_character": "Wallbreaker",
        "spawn_character_interval": 15000,
        "spawn_character_count": 2,
        "spawn_character_start_delay": 5000,
        "id": 72000134,
        "name_en": "Wall Breaker Party"
    },
    {
        "name": "RampUpElixirSpawnWBsMode_Draft",
        "tid": "Wall Breaker Party Draft",
        "card_level_adjustment": "Friendly",
        "deck_selection": "Draft",
        "overtime_seconds": 180,
        "players": "PvP",
        "icon": "icon_mode_1v1",
        "clan_war_description": "Wall Breakers run from the Towers, defend your Tower walls! Draft your deck inside the battle.",
        "spawn_character": "Wallbreaker",
        "spawn_character_interval": 15000,
        "spawn_character_count": 2,
        "spawn_character_start_delay": 5000,
        "id": 72000135,
        "name_en": "Wall Breaker Party Draft"
    },
    {
        "name": "RampUpElixirSpawnWBsMode_2v2_Tournament",
        "tid": "2v2 Wall Breaker Party",
        "card_level_adjustment": "Tournament",
        "deck_selection": "Collection",
        "overtime_seconds": 180,
        "players": "TvT",
        "icon": "icon_mode_2v2",
        "clan_war_description": "Wall Breakers run from the Towers periodically, defend your Tower walls!",
        "spawn_character": "Wallbreaker",
        "spawn_character_interval": 10000,
        "spawn_character_count": 2,
        "spawn_character_start_delay": 5000,
        "id": 72000136,
        "name_en": "2v2 Wall Breaker Party"
    },
    {
        "name": "RampUpElixirSpawnWBsMode_2v2_Draft",
        "tid": "2v2 Wall Breaker Party Draft",
        "card_level_adjustment": "Friendly",
        "deck_selection": "Draft",
        "overtime_seconds": 180,
        "players": "TvT",
        "icon": "icon_mode_2v2",
        "clan_war_description": "Wall Breakers run from the Towers, defend your Tower walls! Draft your deck inside the battle.",
        "spawn_character": "Wallbreaker",
        "spawn_character_interval": 10000,
        "spawn_character_count": 2,
        "spawn_character_start_delay": 5000,
        "id": 72000137,
        "name_en": "2v2 Wall Breaker Party Draft"
    },
    {
        "name": "RampUpElixirSpawnWBsMode_2v2_Ladder",
        "tid": "2v2 Wall Breaker Party",
        "card_level_adjustment": "Ladder",
        "deck_selection": "Collection",
        "overtime_seconds": 180,
        "players": "TvT",
        "icon": "icon_mode_2v2",
        "clan_war_description": "Wall Breakers run from the Towers periodically, defend your Tower walls!",
        "spawn_character": "Wallbreaker",
        "spawn_character_interval": 10000,
        "spawn_character_count": 2,
        "spawn_character_start_delay": 5000,
        "id": 72000138,
        "name_en": "2v2 Wall Breaker Party"
    },
    {
        "name": "RampUpElixirSpawnWBsMode_Friendly",
        "tid": "Wall Breaker Party",
        "card_level_adjustment": "Friendly",
        "deck_selection": "Collection",
        "overtime_seconds": 180,
        "players": "PvP",
        "icon": "icon_mode_1v1",
        "clan_war_description": "Wall Breakers run from the Towers periodically, defend your Tower walls!",
        "spawn_character": "Wallbreaker",
        "spawn_character_interval": 15000,
        "spawn_character_count": 2,
        "spawn_character_start_delay": 5000,
        "id": 72000139,
        "name_en": "Wall Breaker Party"
    },
    {
        "name": "NeutralFisherman_Friendly",
        "tid": "Wild Fisherman Battle",
        "card_level_adjustment": "Friendly",
        "deck_selection": "Collection",
        "overtime_seconds": 180,
        "players": "PvP",
        "icon": "icon_mode_1v1",
        "clan_war_description": "A Fisherman guards the river, pulling nearby troops to his boat!",
        "neutral_character": "Fisherbarrel",
        "id": 72000140,
        "name_en": "Wild Fisherman Battle"
    },
    {
        "name": "NeutralFisherman_Tournament",
        "tid": "Wild Fisherman Battle",
        "card_level_adjustment": "Tournament",
        "deck_selection": "Collection",
        "overtime_seconds": 180,
        "players": "PvP",
        "icon": "icon_mode_1v1",
        "clan_war_description": "A Fisherman guards the river, pulling nearby troops to his boat!",
        "neutral_character": "Fisherbarrel",
        "id": 72000141,
        "name_en": "Wild Fisherman Battle"
    },
    {
        "name": "NeutralFisherman_Ladder",
        "tid": "Wild Fisherman Battle",
        "card_level_adjustment": "Ladder",
        "deck_selection": "Collection",
        "overtime_seconds": 180,
        "players": "PvP",
        "icon": "icon_mode_1v1",
        "clan_war_description": "A Fisherman guards the river, pulling nearby troops to his boat!",
        "neutral_character": "Fisherbarrel",
        "id": 72000142,
        "name_en": "Wild Fisherman Battle"
    },
    {
        "name": "NeutralFisherman_Draft",
        "tid": "Wild Fisherman Draft",
        "card_level_adjustment": "Friendly",
        "deck_selection": "Draft",
        "overtime_seconds": 180,
        "players": "PvP",
        "icon": "icon_mode_1v1",
        "clan_war_description": "A Fisherman guards the river, pulling nearby troops to his boat! Draft your deck inside the battle.",
        "neutral_character": "Fisherbarrel",
        "id": 72000143,
        "name_en": "Wild Fisherman Draft"
    },
    {
        "name": "NeutralFisherman_Draft_2v2",
        "tid": "2v2 Wild Fisherman Draft",
        "card_level_adjustment": "Friendly",
        "deck_selection": "Draft",
        "overtime_seconds": 180,
        "players": "TvT",
        "icon": "icon_mode_2v2",
        "clan_war_description": "A Fisherman guards the river, pulling nearby troops to his boat! Draft your deck inside the battle.",
        "neutral_character": "Fisherbarrel",
        "id": 72000144,
        "name_en": "2v2 Wild Fisherman Draft"
    },
    {
        "name": "NeutralFisherman_Ladder_2v2",
        "tid": "2v2 Wild Fisherman Battle",
        "card_level_adjustment": "Ladder",
        "deck_selection": "Collection",
        "overtime_seconds": 180,
        "players": "TvT",
        "icon": "icon_mode_2v2",
        "clan_war_description": "A Fisherman guards the river, pulling nearby troops to his boat!",
        "neutral_character": "Fisherbarrel",
        "id": 72000145,
        "name_en": "2v2 Wild Fisherman Battle"
    },
    {
        "name": "NeutralFisherman_Tournament_2v2",
        "tid": "2v2 Wild Fisherman Battle",
        "card_level_adjustment": "Tournament",
        "deck_selection": "Collection",
        "overtime_seconds": 180,
        "players": "TvT",
        "icon": "icon_mode_2v2",
        "clan_war_description": "A Fisherman guards the river, pulling nearby troops to his boat!",
        "neutral_character": "Fisherbarrel",
        "id": 72000146,
        "name_en": "2v2 Wild Fisherman Battle"
    },
    {
        "name": "NeutralFisherman_Friendly_2v2",
        "tid": "2v2 Wild Fisherman Battle",
        "card_level_adjustment": "Friendly",
        "deck_selection": "Collection",
        "overtime_seconds": 180,
        "players": "TvT",
        "icon": "icon_mode_2v2",
        "clan_war_description": "A Fisherman guards the river, pulling nearby troops to his boat!",
        "neutral_character": "Fisherbarrel",
        "id": 72000147,
        "name_en": "2v2 Wild Fisherman Battle"
    },
    {
        "name": "CaptureTheFish_Tournament",
        "tid": "Fisherman's Catch",
        "card_level_adjustment": "Tournament",
        "deck_selection": "Collection",
        "overtime_seconds": 180,
        "players": "PvP",
        "icon": "icon_mode_1v1",
        "capturable_building": "FishBoat",
        "capturable_building_respawn_interval": 31500,
        "id": 72000148,
        "name_en": "Fisherman's Catch"
    },
    {
        "name": "BlindDeck_FloodHounds_2v2",
        "tid": "Take To The Skies",
        "request_tid": "Join Classic Decks Battle!",
        "in_progress_tid": "Classic Decks Battle in progress: <cfffffe><time></c>",
        "card_level_adjustment": "Friendly",
        "deck_selection": "Predefined",
        "overtime_seconds": 180,
        "predefined_decks": [
            "FloodHounds_1",
            "FloodHounds_2",
            "FloodHounds_3",
            "FloodHounds_4"
        ],
        "separate_team_decks": true,
        "elixir_production_multiplier": 200,
        "players": "TvT",
        "icon": "icon_mode_2v2",
        "fixed_arena": "Arena_Flood",
        "clan_war_description": "Play with a Classic Deck from King's Cup 1!",
        "id": 72000149,
        "name_en": "Take To The Skies"
    }
]